LICENSE
README.md
setup.py
helliemod/__init__.py
helliemod.egg-info/PKG-INFO
helliemod.egg-info/SOURCES.txt
helliemod.egg-info/dependency_links.txt
helliemod.egg-info/top_level.txt